src/__init__.py
src/src.py
src/stack_database.py
src/stack_queue.py
oparactl-0.0.2.dist-info/LICENSE
oparactl-0.0.2.dist-info/METADATA
oparactl-0.0.2.dist-info/WHEEL
oparactl-0.0.2.dist-info/entry_points.txt
oparactl-0.0.2.dist-info/top_level.txt
oparactl-0.0.2.dist-info/RECORD
